setup.py
scripts/tcpwatch.py
scripts/twill-record
twillrecord/Recorder.py
twillrecord/__init__.py
twillrecord/utils.py
twillrecord.egg-info/PKG-INFO
twillrecord.egg-info/SOURCES.txt
twillrecord.egg-info/dependency_links.txt
twillrecord.egg-info/top_level.txt
twillrecord.egg-info/zip-safe
