Metadata-Version: 1.0
Name: twillrecord
Version: 0.01
Summary: Twill script recorder.
Home-page: http://supreetsethi.net/
Author: Supreet Sethi
Author-email: supreet@phire.com
License: GPL
Keywords: testing benching load performance functional monitoring
Platform: UNKNOWN
Classifier: Development Status :: 4 - Beta
Classifier: Environment :: Console
Classifier: Intended Audience :: Developers
Classifier: Intended Audience :: System Administrators
Classifier: Natural Language :: English
Classifier: License :: OSI Approved :: GNU General Public License (GPL)
Classifier: Operating System :: OS Independent
Classifier: Programming Language :: Python
Classifier: Topic :: Internet :: WWW/HTTP :: Site Management
Classifier: Topic :: Software Development :: Testing
Classifier: Topic :: Software Development :: Quality Assurance
Classifier: Topic :: System :: Benchmark
Classifier: Topic :: System :: Monitoring
